pytest_readme/__init__.py
pytest_readme-1.0.2.dist-info/licenses/LICENSE
pytest_readme-1.0.2.dist-info/METADATA
pytest_readme-1.0.2.dist-info/WHEEL
pytest_readme-1.0.2.dist-info/top_level.txt
pytest_readme-1.0.2.dist-info/RECORD
